{
    "author": [
        "Staff Reporter"
    ], 
    "text": "Seven members of the rival faction of the Manithaneya Makkal Katchi (MMK) on Tuesday night stoned State general secretary Tamim Ansari\u2019s car in Kuniamuthur Police limits. The Police said that they had arrested Abdul Baser, Sahul Hameed, Abbas, Jainuladeen, Mubarak, Mohammad Rafiq and \u2018Auto\u2019 Rafeeq on charges of stoning Mr. Ansari\u2019s car, assaulting a few members of the rival group and also abusing them.\n\nThe incident happened when Mr. Ansari went to the office of one of his confidants, Sudip, in Tiruvalluvar Nagar at Kuniamuthur.\n\nMembers of the rival faction who were there had objected to his entry into the area.\n\nThat led to war of wards between the two groups and the subsequent violence.\n\nThe Police had invoked provision of the Tamil Nadu Public Properties Damages (Prevention of Damages and Loss) Act to arrest the seven. The seven were sent to the Coimbatore Central Prison in judicial custody.", 
    "section": "national", 
    "title": "MMK functionary car stoned", 
    "subsection": "tamilnadu", 
    "date": "2016-02-18"
}