{
    "author": [
        "Special Correspondent"
    ], 
    "text": "Coimbatore Productivity Council will organise a \u201cProductivity Conclave \u2013 2016\u201d on February 25 at The Residency Towers.\n\nAccording to a release, the theme of the conclave is \u201cMake in India: Opportunities and Challenges\u201d and this is the sixth edition of the conclave. V.K. Desai, Managing Director of Tinytech Plants, Gujarat, will be the chief guest. About 400 delegates (senior and middle-level managers) from manufacturing and service sectors are expected to take part.", 
    "section": "national", 
    "title": "Productivity conclave on February 25", 
    "subsection": "tamilnadu", 
    "date": "2016-02-23"
}