{
    "author": [
        "Staff Reporter"
    ], 
    "text": "The ABVP on Sunday lodged two separate police complaints: one against JNU Professor Nivedita Menon for \u201cjustifying\u201d pro-azadi slogans on Jammu and Kashmir and the other against an Associate Dean for giving nod to the controversial Afzal Guru event on February 9.\n\nThe undersigned in both the complaints is Saurabh Sharma, JNU Students\u2019 Union joint secretary.\n\nThe complaints demanding action against the varsity\u2019s teaching and non-teaching staff members were filed at the Vasant Kunj (North) police station. No FIR has been registered yet.\n\nThe complaint says Professor Menon made statements such as \u201cEveryone knows that India is illegally occupying Kashmir. It is said the world over. Everybody accepts (it)\u201d and \u201cManipur and Kashmir have been illegally occupied by the Indian State\u201d.", 
    "section": "national", 
    "title": "Another police complaint against Nivedita Menon", 
    "subsection": "general", 
    "date": "2016-03-14"
}