{
    "author": [
        "Special Correspondent"
    ], 
    "text": "A group of temporary workers stage protest at Ripon Buildings\n\nGarbage collection was partially affected in a few areas of the city following protests by a group of temporary conservancy workers at Ripon Buildings on Thursday. The alleged that they were not paid the full amount of their wages and that many of their demands, including housing facilities, had not been met.\n\nThe protest that started in the morning continued till late in the night.\n\n\u201cIn the evening, senior officials assured us that were would be paid our wages in full, which is Rs. 297 per day. However, they were silent about meeting our other demands,\u201d said G. Munuswamy, joint secretary of Corporation Red Flag Union.\n\nLack of prompt replacement of spare parts in compactors and trucks was another issue that was raised by the protesters, who alleged that accidents caused by Corporation vehicles in the city were on the rise.\n\n\u201cWorkers are seeking an end to the irregularities. We have also demanded regularisation of nominal muster roll workers. At least 908 are on the rolls and 40 have already died,\u201d said Mr. Munuswamy.\n\nThe workers demanded that payment of wages to over 4,000 temporary workers be made on time. The protesters alleged that some workers marked their attendance in a register, but did not report for work to clear garbage.\n\nThere are more than 9,700 permanent conservancy workers on the rolls of the Corporation who record their attendance in the biometric system. They receive a monthly salary, while temporary workers earn Rs. 297 a day.\n\nProtesters said that accidents caused by Corporation vehicles were\n\non the rise", 
    "section": "national", 
    "title": "Conservancy workers stage protest", 
    "subsection": "tamilnadu", 
    "date": "2016-02-05"
}