{
    "author": [
        "Staff Reporter"
    ], 
    "text": "The Social Welfare Department officials stopped a marriage of two minor children.\n\nOfficial sources said that the plan of the families, hailing from Valayapalayam near Palladam, came to light when a person in the village gave a tip-off to the officials.\n\nThe officials warned both the families not to marry off their children till they crossed the stipulated ages prescribed under the law.", 
    "section": "national", 
    "title": "Child marriage stopped", 
    "subsection": "tamilnadu", 
    "date": "2016-03-28"
}