{
    "author": [
        "Special Correspondent"
    ], 
    "text": "Jewellers in the city who gathered at T. Nagar on Friday resorted to a novel form of protest while seeking the rollback of excise duty levied on gold jewellery.\n\nSeveral jewellers, who were wearing T-shirts printed with messages seeking withdrawal of one per cent excise duty, removed them and raised slogans as part of the protest.\n\nFor the third day, jewellery shops in the city remained closed due to the ongoing strike by various associations.\n\nFor the third day, jewellery shops remained closed due to the\n\nongoing strike", 
    "section": "national", 
    "title": "Jewellers continue stir", 
    "subsection": "tamilnadu", 
    "date": "2016-03-12"
}