{
    "author": [], 
    "text": "Flying squad personnel seized 3,775 kg of rice at Krishnapuram near here on Sunday.\n\nThe rice bags, numbering 151, each weighing 25 kg, were being transported without valid document from Thambampatti in Salem district to Perambalur district, a release issued here said.\n\nOld woman robbed\n\nof gold chain\n\nUnidentified persons, on Sunday, robbed Pazhaniammal (60) of her gold chain at a tank near Nagarathar Mandapam at Vaitheeswarankovil when she was taking bath in the tank, police said. Based on a complaint, the police have registered a case and are investigating.", 
    "section": "national", 
    "title": "3,775 kg of rice seized", 
    "subsection": "tamilnadu", 
    "date": "2016-03-14"
}