{
    "author": [
        "Bindu Shajan Perappadan"
    ], 
    "text": "Prevention is better than cure explains office bearers at the Indian Medical Association (IMA), the largest non-government organisation for allopathic doctors in the country \u2014 justifying its one-page note letter addressed to the Union Home Minister Raj Nath Singh recently, stating that they \u201ccondemn the anti-national incident that has taken place recently at JNU.\u201d\n\nThe group stated that the move is also a strong message to all students in medical colleges across the country that \u201canti-national activities will not be tolerated.\u201d\n\n\u201cWe have 50,000 medical students, nursing students, etc, who through this intervention has been told that anti-national incidents have to be curbed and not debated upon,\u201d said IMA honorary secretary general Dr. K.K. Aggarwal speaking to The Hindu .\n\nThe letter meanwhile adds, \u201cWe appeal to the government to take strict and necessary action against any person or organizations or groups carrying out any anti-national protest, speeches, debate or writings in the country.\u201d\n\n\u2013 Bindu Shajan Perappadan", 
    "section": "national", 
    "title": "IMA warns students", 
    "subsection": "general", 
    "date": "2016-02-24"
}